causallearn/__init__.py
causallearn/graph/AdjacencyConfusion.py
causallearn/graph/ArrowConfusion.py
causallearn/graph/Dag.py
causallearn/graph/Edge.py
causallearn/graph/Edges.py
causallearn/graph/Endpoint.py
causallearn/graph/GeneralGraph.py
causallearn/graph/Graph.py
causallearn/graph/GraphClass.py
causallearn/graph/GraphNode.py
causallearn/graph/Node.py
causallearn/graph/NodeType.py
causallearn/graph/NodeVariableType.py
causallearn/graph/SHD.py
causallearn/graph/__init__.py
causallearn/score/LocalScoreFunction.py
causallearn/score/LocalScoreFunctionClass.py
causallearn/score/__init__.py
causallearn/search/__init__.py
causallearn/search/ConstraintBased/CDNOD.py
causallearn/search/ConstraintBased/FCI.py
causallearn/search/ConstraintBased/PC.py
causallearn/search/ConstraintBased/__init__.py
causallearn/search/FCMBased/__init__.py
causallearn/search/FCMBased/ANM/ANM.py
causallearn/search/FCMBased/ANM/__init__.py
causallearn/search/FCMBased/PNL/PNL.py
causallearn/search/FCMBased/PNL/__init__.py
causallearn/search/FCMBased/lingam/CAMUV.py
causallearn/search/FCMBased/lingam/__init__.py
causallearn/search/FCMBased/lingam/base.py
causallearn/search/FCMBased/lingam/bootstrap.py
causallearn/search/FCMBased/lingam/bottom_up_parce_lingam.py
causallearn/search/FCMBased/lingam/causal_effect.py
causallearn/search/FCMBased/lingam/direct_lingam.py
causallearn/search/FCMBased/lingam/hsic.py
causallearn/search/FCMBased/lingam/hsic2.py
causallearn/search/FCMBased/lingam/ica_lingam.py
causallearn/search/FCMBased/lingam/longitudinal_lingam.py
causallearn/search/FCMBased/lingam/multi_group_direct_lingam.py
causallearn/search/FCMBased/lingam/rcd.py
causallearn/search/FCMBased/lingam/var_lingam.py
causallearn/search/FCMBased/lingam/varma_lingam.py
causallearn/search/FCMBased/lingam/utils/__init__.py
causallearn/search/Granger/Granger.py
causallearn/search/Granger/__init__.py
causallearn/search/HiddenCausal/__init__.py
causallearn/search/HiddenCausal/GIN/GIN.py
causal_learn-0.1.4.2.dist-info/METADATA
causal_learn-0.1.4.2.dist-info/WHEEL
causal_learn-0.1.4.2.dist-info/top_level.txt
causal_learn-0.1.4.2.dist-info/RECORD
