Metadata-Version: 2.2
Name: causal-learn
Version: 0.1.4.2
Summary: causal-learn Python Package
Home-page: https://github.com/py-why/causal-learn
Author: 
Classifier: Programming Language :: Python :: 3
Classifier: License :: OSI Approved :: MIT License
Classifier: Operating System :: OS Independent
Requires-Python: >=3.7
Requires-Dist: numpy
Requires-Dist: scipy
Requires-Dist: scikit-learn
Requires-Dist: graphviz
Requires-Dist: statsmodels
Requires-Dist: pandas
Requires-Dist: matplotlib
Requires-Dist: networkx
Requires-Dist: pydot
Requires-Dist: tqdm
Requires-Dist: momentchi2
Dynamic: classifier
Dynamic: description
Dynamic: description-content-type
Dynamic: home-page
Dynamic: requires-dist
Dynamic: requires-python
Dynamic: summary
